clear.py
pycobra.py
pycobra_ce-0.0.3.dist-info/LICENSE
pycobra_ce-0.0.3.dist-info/METADATA
pycobra_ce-0.0.3.dist-info/WHEEL
pycobra_ce-0.0.3.dist-info/top_level.txt
pycobra_ce-0.0.3.dist-info/RECORD
