Metadata-Version: 2.1
Name: pycobra-ce
Version: 0.0.3
Summary: pycobra community edition is a basic vulnerabilty scanner!
Author: Invizabel
Project-URL: Homepage, https://github.com/Invizabel/pycobra
Project-URL: Bug Tracker, https://github.com/Invizabel/pycobra
Classifier: Programming Language :: Python :: 3
Classifier: License :: OSI Approved :: MIT License
Classifier: Operating System :: OS Independent
Requires-Python: >=3.8
License-File: LICENSE
